apis/__init__.py
apis/pc_apis.py
xhs_utils/__init__.py
xhs_utils/common_utils.py
xhs_utils/cookie_util.py
xhs_utils/data_util.py
xhs_utils/xhs_util.py
xhs_yst-0.1.2.dist-info/METADATA
xhs_yst-0.1.2.dist-info/WHEEL
xhs_yst-0.1.2.dist-info/entry_points.txt
xhs_yst-0.1.2.dist-info/top_level.txt
xhs_yst-0.1.2.dist-info/RECORD
