Metadata-Version: 2.4
Name: xhs_yst
Version: 0.1.2
Summary: 小红书爬虫工具
Home-page: 
Author: yst
Classifier: Programming Language :: Python :: 3
Classifier: License :: OSI Approved :: MIT License
Classifier: Operating System :: OS Independent
Requires-Python: >=3.6
Requires-Dist: PyExecJS
Requires-Dist: requests
Requires-Dist: loguru
Requires-Dist: python-dotenv
Requires-Dist: retry
Requires-Dist: openpyxl
Dynamic: author
Dynamic: classifier
Dynamic: description
Dynamic: description-content-type
Dynamic: requires-dist
Dynamic: requires-python
Dynamic: summary
